sandman2/__init__.py
sandman2/__main__.py
sandman2/admin.py
sandman2/app.py
sandman2/decorators.py
sandman2/exception.py
sandman2/model.py
sandman2/service.py
sandman2/templates/create.html
sandman2/templates/edit.html
sandman2/templates/layout.html
sandman2/templates/list.html
sandman2-1.2.3.dist-info/LICENSE
sandman2-1.2.3.dist-info/METADATA
sandman2-1.2.3.dist-info/WHEEL
sandman2-1.2.3.dist-info/entry_points.txt
sandman2-1.2.3.dist-info/top_level.txt
sandman2-1.2.3.dist-info/RECORD
