Metadata-Version: 2.1
Name: sandman2
Version: 1.2.3
Summary: Automated REST APIs for legacy (existing) databases
Home-page: http://github.com/jeffknupp/sandman2/
Author: Jeff Knupp
Author-email: jeff@jeffknupp.com
License: Apache Software License
Platform: any
Classifier: Programming Language :: Python
Classifier: Programming Language :: Python :: 2
Classifier: Programming Language :: Python :: 3
Classifier: Development Status :: 4 - Beta
Classifier: Natural Language :: English
Classifier: Environment :: Web Environment
Classifier: Intended Audience :: Developers
Classifier: License :: OSI Approved :: Apache Software License
Classifier: Operating System :: OS Independent
Classifier: Topic :: Software Development :: Libraries :: Python Modules
Classifier: Topic :: Software Development :: Libraries :: Application Frameworks
Classifier: Topic :: Internet :: WWW/HTTP :: Dynamic Content
Requires-Dist: Flask (>=1.0.3)
Requires-Dist: Flask-SQLAlchemy (==2.4.0)
Requires-Dist: SQLAlchemy (==1.3.3)
Requires-Dist: Flask-Admin (>=1.5.3)
Requires-Dist: Flask-HTTPAuth (>=3.2.4)
